Metadata-Version: 1.1
Name: edipy
Version: 0.0.2
Summary: Parser positional files
Home-page: https://github.com/fakeezz/edipy
Author: fakeezz
Author-email: fakeezz@gmail.com
License: MIT
Download-URL: https://github.com/fakeezz/edipy/tarball/0.0.2
Platform: any
Classifier: Programming Language :: Python
Classifier: Operating System :: OS Independent
